FastCoding/__init__.py
FastCoding/backend/__init__.py
FastCoding/backend/logging.py
FastCoding/backend/config/__init__.py
FastCoding/backend/config/links.py
FastCoding/backend/config/permission.py
FastCoding/backend/database/Stats_db.py
FastCoding/backend/database/__init__.py
FastCoding/backend/database/autodelete_db.py
FastCoding/backend/database/globalchat_db.py
FastCoding/backend/database/levelroles_db.py
FastCoding/backend/database/logging_db.py
FastCoding/backend/database/notes_db.py
FastCoding/backend/database/spam_db.py
FastCoding/backend/database/vc_db.py
FastCoding/backend/database/warn_db.py
FastCoding/backend/database/welcome_db.py
FastCoding/backend/utils/__init__.py
FastCoding/backend/utils/config.py
FastCoding/backend/utils/utils.py
FastCoding/ui/__init__.py
FastCoding/ui/emojis.py
FastCoding/ui/templates/__init__.py
FastCoding/ui/templates/embeds.py
fastcoding-0.1.0.dist-info/METADATA
fastcoding-0.1.0.dist-info/WHEEL
fastcoding-0.1.0.dist-info/top_level.txt
fastcoding-0.1.0.dist-info/RECORD
