Metadata-Version: 2.4
Name: fastcoding
Version: 0.1.0
Summary: A Python package for fast and structured coding utilities
Author: Pascal
License: MIT
Project-URL: Homepage, https://github.com/deinname/fastcoding
Requires-Python: >=3.8
